---
title: 18.字节码操作指令
tags: []
---

##### 加载和存储指令

&#8195;&#8195;加载和存储指令用于将数据在栈桢中的局部变量表和操作数栈之间来回传输。
- 将一个局部变量表加载到操作栈：iload、iload_&lt;n&gt;、lload、lload_&lt;n&gt;、fload、fload_&lt;n&gt;、dload、dload_&lt;n&gt;、aload、aload_&lt;n&gt;。
- 将一个数值从操作数栈存储到局部变量表：istore、istore_&lt;n&gt;、lstore、lstore_&lt;n&gt;、fstore、fstore_&lt;n&gt;、dstroe、dstore_&lt;n&gt;、astroe、astroe_&lt;n&gt;。
- 将一个常量添加到操作数栈:bipush、sipush、ldc、ldc_w、ldc2_2、aconst_null、iconst_m1、iconst_&lt;i&gt;、iconst_&lt;l&gt;、fconst_&lt;f&gt;、dconst&lt;d&gt;。
- 扩充局部变量表的访问索引的指令：wide。
以上指令中以&lt;&gt;结尾的，这些指令实际上代表了一组指令（iload_&lt;n&gt;代表了iload_0、iload_1和iload_2这几条指令）。

##### 运算指令

&#8195;&#8195;运算或算法指令用于对两个操作数栈上的值进行某种特定运算，并把结果重新存入到操作栈顶。
- 加法指令：iadd、ladd、fadd、dadd。
- 减法指令：isub、lsub、fsub、dsub。
- 乘法指令：imul、lmul、fmul、dmul。
- 除法指令：idiv、ldiv、fdiv、ddiv。
- 求余指令：irem、lrem、frem、drem。
- 取反指令：ineg、lneg、fneg、dneg。
- 位移指令： ishl、ishr、iushr、lshl、lshr、lushr。
- 按位或指令：ior、lor。
- 按位与指令：iand、land。
- 按位异或指令： ixor、lxor。
- 局部变量自增指令：iinc。
- 比较指令：dcmpg、dcmpl、fcmpg、fcmpl、lcmp。

##### 类型转换指令

&#8195;&#8195;类型转换指令可以将两种不同的数值类型进行相互转换。当进行宽化型转换（小范围类型向大范围类型的安全转换：int a = short(123)，无需显示的转换指令，相对的进行处理窄化类型转换时（ 大范围类型向小范围类型的转换），必须显示的使用指令来完成，这些指令包括：i2b、i2c、i2s、l2i、f2i、f2l、d2i、d2l和d2f。窄化类型转换可能会导致转换结果产生不同的正负号、不同的数量级的情况，

##### 对象创建与访问指令

&#8195;&#8195;虽然实例和数组都是对象，但是Java虚拟机对类实例和数组的创建与操作使用了不同的字节码指令。
- 创建类实例的指令：new。
- 创建数组的指令：newarray、anewarray、multiannewarray。
- 访问类字段（static字段 or 类变量）和实例变量的指令：getfield、putfield、getstatic、putstatic。
- 把一个数组元素加载到操作数栈的指令：baload、caload、saload、iaload、laload、faload、daload、aaload。
- 将一个操作数栈的值存储到数组元素的指令：bastore、castore、sastore、iastore、fastore、dastore、aastore。
- 取数组长度的指令：arraylength。
检查类实例类型的指令：instanceof、checkcast。

##### 操作数栈管理指令

&#8195;&#8195;如同操作一个普通数据结构中的堆栈那样，Java虚拟机提供了一些用于直接操作操作数栈的指令：
- 将操作数栈的栈顶一个或两个元素出栈：pop、pop2。
- 复制栈顶一个或两个数值并将复制值或双份的复制值重新压入栈顶dup、dup2、dup_x1、dup2_x1、dup_x2、dup2_x2。
- 将栈顶最顶端的两个数值互换：swap。

##### 控制转移指令

&#8195;&#8195;控制转移指令可以让虚拟机有条件或无条件地从指定的位置指令而不是控制转移指令的下一条指令继续执行程序，可以认为**控制指令就是在有条件或无条件地修改PC寄存器的值**。
- 条件分支：ifeq、iflt、ifle、ifne、ifgt、ifge、ifnull、ifnonnull、if_icmpeq、if_icmpne、if_icmplt、if_icmpgt、if_icmple、if_icmpge、if_acmpeq和if_acmpne。
- 复合条件分支：tableswitch、lookupswitch。
- 无条件分支：goto、goto_w、jsr、jsr_w、ret。

##### 方法调用和返回指令
- invokevirtual指令用于调用对象的实例方法，根据对象的实际类型进行分派，Java语言中最常见的方法分派方式。
- invokeinterface指令用于调用接口方法，它会在运行时搜索一个实现了这个接口方法的对象，找出适合的方法进行调用。
- invokespecial指令用于调用一些需要特殊处理的实例方法，包括实例初始化方法、私有方法和父类方法。
- invokestatic指令用于调用类方法。
- invokedynamic指令用于在运行时动态解析出调用点限定符所引用的方法，并执行该方法，其他4条调用指令的分派逻辑固化在Java虚拟机内部，而invokedynamic指令的分派逻辑是由用户所设定的引导方法决定的。
- 方法调用指令与数据类型无关，而方法返回指令是根据返回值的类型区分的，包括ireturn（当返回值是boolean、byte、char、short、int类型时使用）、lreturn、freturn、dreturn、areturn，另外还有一条return指令供生命为void的方法只用。

##### 异常处理指令

&#8195;&#8195;显示抛出异常的操作都由athrow指令来实现，除了用throw语句显示抛出异常之外，Java虚拟机规范还规定了许多运行时异常会在虚拟机指令检测到异常状态自动抛出，如：`1 / 0` 虚拟机会在idiv或ldiv指令中抛出`ArithmeticException`异常。

##### 同步指令

&#8195;&#8195;Java虚拟机可以支持方法级的同步和方法内部一段指令序列的同步，这两种同步结构都是使用管程（Monitor）来支持的。
方法级的同步是隐式的，即无需通过字节码指令来控制，它无须通过字节码指令来控制，它实现在方法调用和返回操作之中。虚拟机可以从方法常量池的方法表结构的方法表结构中的ACC_SYNCHRONIZED访问标志得知一个方法是否声明为同步方法，当方法调用时，调用指令将会检查方法的ACC_SYNCHRONIZED访问标志是否被设置，如果设置了，执行线程就要求先成功持有管程，然后才能执行方法，最后当方法完成时释放管程。在方法执行期间，执行线程持有了管程，其他线程都无法再获取到同一个管程。

&#8195;&#8195;同步一段指令集序列通常是由Java语言中的synchronized语句块表示，Java虚拟机有`monitorenter`和`monitorexit`两条指令来支持synchronized关键字的语义。
```java
public void add(){
       synchronized (this){
            aa();
       }
   }

Code:
      stack=2, locals=3, args_size=1
         0: aload_0
         1: dup
         2: astore_1
         3: monitorenter
         4: aload_0
         5: invokespecial #2                  // Method aa:()V
         8: aload_1
         9: monitorexit
        10: goto          18
        13: astore_2
        14: aload_1
        15: monitorexit
        16: aload_2
        17: athrow
        18: return
      Exception table:
         from    to  target type
             4    10    13   any
            13    16    13   any
```
